LICENSE
MANIFEST.in
README.rst
setup.cfg
setup.py
bin/orcsome
orcsome/__init__.py
orcsome/__main__.py
orcsome/actions.py
orcsome/aliases.py
orcsome/ev.py
orcsome/ev_build.py
orcsome/notify.py
orcsome/run.py
orcsome/testwm.py
orcsome/utils.py
orcsome/wm.py
orcsome/wrappers.py
orcsome/xlib.py
orcsome/xlib_build.py
orcsome.egg-info/PKG-INFO
orcsome.egg-info/SOURCES.txt
orcsome.egg-info/dependency_links.txt
orcsome.egg-info/not-zip-safe
orcsome.egg-info/requires.txt
orcsome.egg-info/top_level.txt
orcsome/__pycache__/_cffi__x26cf2f06x3c566d49.c
orcsome/__pycache__/_cffi__x703cd531x78635c57.c