Metadata-Version: 1.1
Name: orcsome
Version: 0.6
Summary: Scripting extension for NETWM compliant window managers
Home-page: https://github.com/baverman/orcsome
Author: Anton Bobrov
Author-email: bobrov@vl.ru
License: UNKNOWN
Platform: UNKNOWN
Classifier: Programming Language :: Python
Classifier: Programming Language :: Python :: 2.7
Classifier: License :: OSI Approved :: MIT License
Classifier: Development Status :: 4 - Beta
Classifier: Environment :: X11 Applications
Classifier: Topic :: Desktop Environment :: Window Managers
Classifier: Intended Audience :: Developers
Classifier: Intended Audience :: End Users/Desktop
Classifier: Natural Language :: English
